file_remover/main.py
file_remover-0.1.2.dist-info/METADATA
file_remover-0.1.2.dist-info/WHEEL
file_remover-0.1.2.dist-info/entry_points.txt
file_remover-0.1.2.dist-info/RECORD
